Metadata-Version: 2.4
Name: adafruit-circuitpython-oauth2
Version: 1.0.23
Summary: CircuitPython helper for OAuth2.0 authorization to access Google APIs.
Author-email: Adafruit Industries <circuitpython@adafruit.com>
License: MIT
Project-URL: Homepage, https://github.com/adafruit/Adafruit_CircuitPython_OAuth2
Keywords: adafruit,blinka,circuitpython,micropython,oauth2,oauth,api,google
Classifier: Intended Audience :: Developers
Classifier: Topic :: Software Development :: Libraries
Classifier: Topic :: Software Development :: Embedded Systems
Classifier: Topic :: System :: Hardware
Classifier: License :: OSI Approved :: MIT License
Classifier: Programming Language :: Python :: 3
License-File: LICENSE
Requires-Dist: Adafruit-Blinka
Requires-Dist: adafruit-circuitpython-requests
Provides-Extra: optional
Dynamic: license-file
